geo_marker_extraction/__init__.py
geo_marker_extraction/case_study.py
geo_marker_extraction/cluster.py
geo_marker_extraction/maps.py
geo_marker_extraction/markers.py
geo_marker_extraction/separation.py
geo_marker_extraction/viz.py
geo_marker_extraction-0.0.0.dist-info/licenses/LICENSE
geo_marker_extraction-0.0.0.dist-info/METADATA
geo_marker_extraction-0.0.0.dist-info/WHEEL
geo_marker_extraction-0.0.0.dist-info/top_level.txt
geo_marker_extraction-0.0.0.dist-info/RECORD
