Metadata-Version: 2.4
Name: geo-marker-extraction
Version: 0.0.0
Summary: Extract markers from collections of geo-referenced images
Author-email: John Gardner <gardner.john97@gmail.com>, Harri Ravenscroft <harri.ravenscroft@hotmail.co.uk>
License: MIT License
Project-URL: Homepage, https://github.com/jla-gardner/geo-marker-extraction
Classifier: License :: OSI Approved :: MIT License
Classifier: Programming Language :: Python
Classifier: Programming Language :: Python :: 3
Requires-Python: >=3.11
License-File: LICENSE
Requires-Dist: jaxtyping>=0.2.36
Requires-Dist: locache>=4.0.2
Requires-Dist: matplotlib>=3.9.4
Requires-Dist: networkx>=3.5
Requires-Dist: numpy>=2.0.2
Requires-Dist: opencv-python>=4.11.0.86
Requires-Dist: optuna>=4.5.0
Requires-Dist: pandas>=2.3.2
Requires-Dist: pillow>=11.3.0
Requires-Dist: rdp>=0.8
Requires-Dist: scikit-learn>=1.6.1
Provides-Extra: demo
Requires-Dist: folium>=0.20.0; extra == "demo"
Requires-Dist: ipywidgets>=8.1.7; extra == "demo"
Requires-Dist: notebook>=7.4.5; extra == "demo"
Dynamic: license-file
